octobrowser/__init__.py
octobrowser/exceptions.py
octobrowser/globals.py
octobrowser/types.py
octobrowser/utils.py
octobrowser-0.1.0a1.dev1.dist-info/LICENSE
octobrowser-0.1.0a1.dev1.dist-info/METADATA
octobrowser-0.1.0a1.dev1.dist-info/WHEEL
octobrowser-0.1.0a1.dev1.dist-info/RECORD
