Metadata-Version: 2.1
Name: octobrowser
Version: 0.1.0a1.dev1
Summary: The package for interacting with API of anti-detect browser Octobrowser.
Home-page: https://github.com/blnkoff/octobrowser
License: MIT
Author: Alexey 
Author-email: axbelenkov@gmail.com
Requires-Python: >=3.11,<4.0
Classifier: Development Status :: 1 - Planning
Classifier: Intended Audience :: Developers
Classifier: License :: OSI Approved :: MIT License
Classifier: Operating System :: MacOS
Classifier: Operating System :: Microsoft :: Windows
Classifier: Programming Language :: Python :: 3
Classifier: Programming Language :: Python :: 3.11
Classifier: Programming Language :: Python :: 3.12
Classifier: Programming Language :: Python :: 3 :: Only
Classifier: Topic :: Software Development :: Libraries :: Python Modules
Project-URL: Repository, https://github.com/blnkoff/octobrowser
